tvrenamr/__init__.py
tvrenamr/config.py
tvrenamr/errors.py
tvrenamr/frontend.py
tvrenamr/libraries.py
tvrenamr/logs.py
tvrenamr/main.py
tvrenamr/options.py
tvrenamr/tvdb.py
tvrenamr/cli/__init__.py
tvrenamr/cli/core.py
tvrenamr/cli/helpers.py
tvrenamr/vendor/__init__.py
tvrenamr/vendor/defusedxml/ElementTree.py
tvrenamr/vendor/defusedxml/__init__.py
tvrenamr/vendor/defusedxml/cElementTree.py
tvrenamr/vendor/defusedxml/common.py
tvrenamr/vendor/defusedxml/expatbuilder.py
tvrenamr/vendor/defusedxml/expatreader.py
tvrenamr/vendor/defusedxml/lxml.py
tvrenamr/vendor/defusedxml/minidom.py
tvrenamr/vendor/defusedxml/pulldom.py
tvrenamr/vendor/defusedxml/sax.py
tvrenamr/vendor/defusedxml/xmlrpc.py
tvrenamr/vendor/requests/__init__.py
tvrenamr/vendor/requests/adapters.py
tvrenamr/vendor/requests/api.py
tvrenamr/vendor/requests/auth.py
tvrenamr/vendor/requests/certs.py
tvrenamr/vendor/requests/compat.py
tvrenamr/vendor/requests/cookies.py
tvrenamr/vendor/requests/exceptions.py
tvrenamr/vendor/requests/hooks.py
tvrenamr/vendor/requests/models.py
tvrenamr/vendor/requests/sessions.py
tvrenamr/vendor/requests/status_codes.py
tvrenamr/vendor/requests/structures.py
tvrenamr/vendor/requests/utils.py
tvrenamr/vendor/requests/packages/__init__.py
tvrenamr/vendor/requests/packages/chardet/__init__.py
tvrenamr/vendor/requests/packages/chardet/big5freq.py
tvrenamr/vendor/requests/packages/chardet/big5prober.py
tvrenamr/vendor/requests/packages/chardet/chardetect.py
tvrenamr/vendor/requests/packages/chardet/chardistribution.py
tvrenamr/vendor/requests/packages/chardet/charsetgroupprober.py
tvrenamr/vendor/requests/packages/chardet/charsetprober.py
tvrenamr/vendor/requests/packages/chardet/codingstatemachine.py
tvrenamr/vendor/requests/packages/chardet/compat.py
tvrenamr/vendor/requests/packages/chardet/constants.py
tvrenamr/vendor/requests/packages/chardet/cp949prober.py
tvrenamr/vendor/requests/packages/chardet/escprober.py
tvrenamr-4.4.0.dist-info/DESCRIPTION.rst
tvrenamr-4.4.0.dist-info/METADATA
tvrenamr-4.4.0.dist-info/RECORD
tvrenamr-4.4.0.dist-info/WHEEL
tvrenamr-4.4.0.dist-info/entry_points.txt
tvrenamr-4.4.0.dist-info/metadata.json
tvrenamr-4.4.0.dist-info/top_level.txt
