Metadata-Version: 2.0
Name: tvrenamr
Version: 4.4.0
Summary: Rename tv show files using online databases
Home-page: http://tvrenamr.info
Author: George Hickman
Author-email: george@ghickman.co.uk
License: MIT
Platform: UNKNOWN
Classifier: Development Status :: 6 - Mature
Classifier: Environment :: Console
Classifier: Intended Audience :: End Users/Desktop
Classifier: License :: OSI Approved :: MIT License
Classifier: Natural Language :: English
Classifier: Operating System :: MacOS :: MacOS X
Classifier: Operating System :: POSIX
Classifier: Programming Language :: Python :: 2
Classifier: Programming Language :: Python :: 2.6
Classifier: Programming Language :: Python :: 2.7
Classifier: Programming Language :: Python :: 3
Classifier: Programming Language :: Python :: 3.3
Classifier: Topic :: Utilities
Requires-Dist: click
Requires-Dist: defusedxml
Requires-Dist: pyyaml
Requires-Dist: requests
